auth0_template/__init__.py
auth0_template/tracker.py
auth0_open_source_template-20.1.0.dist-info/METADATA
auth0_open_source_template-20.1.0.dist-info/WHEEL
auth0_open_source_template-20.1.0.dist-info/top_level.txt
auth0_open_source_template-20.1.0.dist-info/RECORD
